Memoria_de_dados.v
module data_memory (
    input wire        clk,
    input wire        mem_read,
    input wire        mem_write,
    input wire        load_byte,    // 1 para lb
    input wire        store_byte,   // 1 para sb
    input wire [31:0] addr,
    input wire [31:0] write_data,
    output reg [31:0] read_data
);

    // Memória byte-endereçável com 4KB
    reg [7:0] memory [0:4095];

    wire [11:0] byte_addr = addr[13:2]; // endereçamento em bytes (ajustável ao tamanho da memória)

    always @(posedge clk) begin
        if (mem_write) begin
            if (store_byte) begin
                memory[addr] <= write_data[7:0]; // escreve apenas 1 byte
            end else begin
                // escreve os 4 bytes da palavra
                memory[addr]     <= write_data[7:0];
                memory[addr + 1] <= write_data[15:8];
                memory[addr + 2] <= write_data[23:16];
                memory[addr + 3] <= write_data[31:24];
            end
        end
    end

    always @(*) begin
        if (mem_read) begin
            if (load_byte) begin
                // Leitura de 1 byte com extensão de sinal
                read_data = {{24{memory[addr][7]}}, memory[addr]};
            end else begin
                // Leitura de 4 bytes como palavra
                read_data = { memory[addr + 3],
                              memory[addr + 2],
                              memory[addr + 1],
                              memory[addr] };
            end
        end else begin
            read_data = 32'b0;
        end
    end

endmodule

Memoria_de_instrucao.v
module instr_memory (
    input  wire        clk,           // Ja que tem escrita em registrador, melhor colocar
    input  wire        write,         // Sinal de controle sincrono
    input  wire [31:0] addr,          // Endereço da instrução (PC)
    input  wire [31:0] inst_input,    // Instrução a ser gravada
    output wire [31:0] instruction    // Instrução lida
);

    // Memória com 256 posições de 32 bits
    reg [31:0] memory [0:255];

    // Escrita síncrona na memória (manual)
    always @(posedge clk) begin
        if (write)
            memory[addr[31:2]] <= inst_input;
    end

    assign instruction = memory[addr[31:2]];

endmodule

PC.v
module program_counter (
    input wire clk,           //-> clock
    input wire reset,         //-> sinal de reset
    input wire [31:0] pc_in,  //-> valor de entrada (novo endereço)
    output reg [31:0] pc_out  //-> valor de saída (endereço atual)
);

    always @(posedge clk or posedge reset) begin
        if (reset)
            pc_out <= 32'b0;           
        else
            pc_out <= pc_in;           
    end

endmodule

Controle_de_branch.v
module branch_control (
    input  wire        branch,      // Sinal da unidade de controle
    input  wire        zero,        // Flag de igualdade da ALU
    input  wire [31:0] pc_plus_4,   // PC + 4 (próxima instrução normal)
    input  wire [31:0] pc_branch,   // PC + offset (caso branch)
    output wire [31:0] pc_next      // Próximo PC
);

    assign pc_next = (branch && zero) ? pc_branch : pc_plus_4;

endmodule

ULA_nova.v
module alu (
    input  wire [31:0] a,
    input  wire [31:0] b,
    input  wire [3:0]  alu_ctrl,
    output reg  [31:0] result,
    output reg         zero,
    output reg         carry,
    output reg         overflow
);

    always @(*) begin
        carry    = 0;
        overflow = 0;

        case (alu_ctrl)
            4'b0010: begin // Soma (ADD)
                {carry, result} = a + b;
                overflow = (a[31] == b[31]) && (result[31] != a[31]);
            end
            4'b0110: begin // Subtração (SUB)
                result   = a - b;
                overflow = (a[31] != b[31]) && (result[31] != a[31]);
            end
            4'b0000: result = a & b;        // AND
            4'b0001: result = a | b;        // OR
            4'b0100: result = a ^ b;        // XOR (added for completeness)
            4'b1000: result = a << b[4:0];  // SLL (Shift Left Logical)
            4'b1001: result = a >> b[4:0];  // SRL (Shift Right Logical)
            4'b1010: result = $signed(a) >>> b[4:0]; // SRA (Shift Right Arithmetic) - added
            4'b0111: result = (a < b) ? 32'b1 : 32'b0; // SLT (Set Less Than) - added
            4'b1011: result = ($unsigned(a) < $unsigned(b)) ? 32'b1 : 32'b0; // SLTU - added
            default: result = 32'b0;
        endcase

        zero = (result == 32'b0);
    end
endmodule

Unidade_de_controle_ULA.v
module alu_control (
    input wire [1:0] alu_op,
    input wire [2:0] funct3,
    input wire [6:0] funct7, // geralmente instr[30] para R-type
    output reg [3:0] alu_ctrl
);

    always @(*) begin
        case (alu_op)
            2'b00: alu_ctrl = 4'b0010; // lw/sw/addi → soma
            2'b01: alu_ctrl = 4'b0110; // beq → subtração
            2'b10: begin // R-type ou I-type lógico
                case (funct3)
                    3'b000: begin // add/addi or sub
                        if (funct7[5] == 1'b1) // sub (only for R-type)
                            alu_ctrl = 4'b0110; 
                        else
                            alu_ctrl = 4'b0010; // add/addi
                    end
                    3'b111: alu_ctrl = 4'b0000; // and/andi
                    3'b110: alu_ctrl = 4'b0001; // or/ori
                    3'b100: alu_ctrl = 4'b0100; // xor/xori
                    3'b001: alu_ctrl = 4'b1000; // sll/slli
                    3'b101: begin // srl/srli or sra/srai
                        if (funct7[5] == 1'b1) // sra/srai
                            alu_ctrl = 4'b1010;
                        else
                            alu_ctrl = 4'b1001; // srl/srli
                    end
                    3'b010: alu_ctrl = 4'b0111; // slt/slti
                    3'b011: alu_ctrl = 4'b1011; // sltu/sltiu
                    default: alu_ctrl = 4'b1111;
                endcase
            end
            default: alu_ctrl = 4'b1111;
        endcase
    end
endmodule

GenImm.v
module imm_gen (
    input wire [31:0] instr,         // Instrução
    output reg [31:0] imm_out        // Imediato expandido
);

    wire [6:0] opcode = instr[6:0];  // opcode que determina o tipo

    always @(*) begin
        case (opcode)
            7'b0010011, // I-type: addi, ori, andi...
            7'b0000011, // I-type: lw
            7'b1100111: // I-type: jalr
                imm_out = {{20{instr[31]}}, instr[31:20]};

            7'b0100011: begin // S-type: sw, sb, sh
                imm_out = {{20{instr[31]}}, instr[31:25], instr[11:7]};
            end

            7'b1100011: begin // B-type: beq, bne, etc.
                imm_out = {{19{instr[31]}}, instr[31], instr[7], instr[30:25], instr[11:8], 1'b0};
            end

            7'b0010111, // U-type: auipc
            7'b0110111: // U-type: lui
                imm_out = {instr[31:12], 12'b0};

            7'b1101111: begin // J-type: jal
                imm_out = {{11{instr[31]}}, instr[31], instr[19:12], instr[20], instr[30:21], 1'b0};
            end

            default: imm_out = 32'b0; // fallback
        endcase
    end

endmodule

banco_reg_32.v
// Banco de registradores de 32 bits

module registradores(
    input clk,
    input [4:0] rs1, // Registrador de leitura 1
    input [4:0] rs2, // Registrador de leitura 2
    input [4:0] rd, // Registrador de escrita
    input [31:0] write_data, // Dados a serem escritos
    input reg_write, // Habilita escrita no registrador
    output reg [31:0] read_data1, // Dados lidos do registrador 1
    output reg [31:0] read_data2 // Dados lidos do registrador 2
);

    reg [31:0] registers [31:0]; // Array de 32 de registradores de 32 bits

    integer i;
    initial begin
        for (i = 0; i < 32; i = i + 1) begin
            registers[i] = 32'h00000000;
        end
    end

    always @(posedge clk) begin
        if (reg_write) begin
            if (rd != 5'd0) // Verifica se não é o registrador zero
                registers[rd] <= write_data; // Escreve dados no registrador especificado
        end
    end

    always @(*) begin
        read_data1 = registers[rs1]; // Lê dados do registrador 1
        read_data2 = registers[rs2]; // Lê dados do registrador 2
    end
endmodule

Unidade_de_controle.v
module control_unit (
    input  wire [6:0] opcode,    // instr[6:0]
    output reg       reg_write,
    output reg       mem_to_reg,
    output reg       mem_read,
    output reg       mem_write,
    output reg       alu_src,
    output reg [1:0] alu_op,
    output reg       branch
);

    always @(*) begin
        case (opcode)
            7'b0110011: begin // R-type (add, sub, and, or...)
                reg_write   = 1;
                mem_to_reg  = 0;
                mem_read    = 0;
                mem_write   = 0;
                alu_src     = 0;
                alu_op      = 2'b10;
                branch     = 0;
            end
            7'b0000011: begin // lw (I-type)
                reg_write   = 1;
                mem_to_reg  = 1;
                mem_read    = 1;
                mem_write   = 0;
                alu_src     = 1;
                alu_op      = 2'b00;
                branch     = 0;
            end
            7'b0100011: begin // sw (S-type)
                reg_write   = 0;
                mem_to_reg  = 0; // irrelevante
                mem_read    = 0;
                mem_write   = 1;
                alu_src     = 1;
                alu_op      = 2'b00;
                branch     = 0;
            end
            7'b1100011: begin // beq, bne (B-type)
                reg_write   = 0;
                mem_to_reg  = 0;
                mem_read    = 0;
                mem_write   = 0;
                alu_src     = 0;
                alu_op      = 2'b01;
                branch     = 1;
            end
            7'b0010011: begin // addi, ori, andi (I-type)
                reg_write   = 1;
                mem_to_reg  = 0;
                mem_read    = 0;
                mem_write   = 0;
                alu_src     = 1;
                alu_op      = 2'b10;
                branch     = 0;
            end
            default: begin // default (NOP)
                reg_write   = 0;
                mem_to_reg  = 0;
                mem_read    = 0;
                mem_write   = 0;
                alu_src     = 0;
                alu_op      = 2'b00;
                branch     = 0;
            end
        endcase
    end
endmodule

RiscVTop.v
`include "Unidade_de_controle.v"
`include "banco_reg_32.v"
`include "GenImm.v"
`include "Unidade_de_controle_ULA.v"
`include "ULA_nova.v"
`include "Controle_de_branch.v"
`include "PC.v"
`include "Memoria_de_instrucao.v"
`include "Memoria_de_dados.v"


module riscv_top (
    input wire clk,
    input wire reset
);

    // === Fios e sinais ===
    wire [31:0] pc_current;
    wire [31:0] pc_next;
    wire [31:0] pc_plus4;
    wire [31:0] instruction;

    // Fios para campos da instrução
    wire [6:0] opcode = instruction[6:0];
    wire [4:0] rd     = instruction[11:7];
    wire [2:0] funct3 = instruction[14:12];
    wire [4:0] rs1    = instruction[19:15];
    wire [4:0] rs2    = instruction[24:20];
    wire [6:0] funct7 = instruction[31:25];

    // Unidade de Controle
    wire alu_src, mem_to_reg, reg_write, mem_read, mem_write, branch;
    wire [1:0] alu_op;

    control_unit CU (
        .opcode(opcode),
        .reg_write(reg_write),
        .mem_to_reg(mem_to_reg),
        .mem_read(mem_read),
        .mem_write(mem_write),
        .alu_src(alu_src),
        .alu_op(alu_op),
        .branch(branch)
    );

    // Registradores
    wire [31:0] reg_data1, reg_data2, reg_write_data;
    registradores RF (
        .clk(clk),
        .rs1(rs1),
        .rs2(rs2),
        .rd(rd),
        .write_data(reg_write_data),
        .reg_write(reg_write),
        .read_data1(reg_data1),
        .read_data2(reg_data2)
    );

    // Imediato
    wire [31:0] imm_out;
    imm_gen IMM (
        .instr(instruction),
        .imm_out(imm_out)
    );

    // ALU control
    wire [3:0] alu_ctrl;
    alu_control ALUCTRL (
        .alu_op(alu_op),
        .funct3(funct3),
        .funct7(funct7),
        .alu_ctrl(alu_ctrl)
    );

    // Mux ALU src
    wire [31:0] alu_in2;
    assign alu_in2 = (alu_src) ? imm_out : reg_data2;

    // ALU
    wire [31:0] alu_result;
    wire zero, carry, overflow;
    alu ALU (
        .a(reg_data1),
        .b(alu_in2),
        .alu_ctrl(alu_ctrl),
        .result(alu_result),
        .zero(zero),
        .carry(carry),
        .overflow(overflow)
    );

    // PC + 4
    assign pc_plus4 = pc_current + 4;

    // PC + imediato (branch)
    wire [31:0] pc_branch = pc_current + imm_out;

    // Branch control (PC mux)
    branch_control BRCTRL (
        .branch(branch),
        .zero(zero),
        .pc_plus_4(pc_plus4),
        .pc_branch(pc_branch),
        .pc_next(pc_next)
    );

    // PC
    program_counter PCREG (
        .clk(clk),
        .reset(reset),
        .pc_in(pc_next),
        .pc_out(pc_current)
    );

    // Memória de instrução
    instr_memory IMEM (
        .addr(pc_current),
        .instruction(instruction)
    );

    // Memória de dados
    wire [31:0] data_memory_out;
    wire load_byte = (opcode == 7'b0000011 && funct3 == 3'b000);
    wire store_byte = (opcode == 7'b0100011 && funct3 == 3'b000);

    data_memory DMEM (
        .clk(clk),
        .mem_read(mem_read),
        .mem_write(mem_write),
        .load_byte(load_byte),
        .store_byte(store_byte),
        .addr(alu_result),
        .write_data(reg_data2),
        .read_data(data_memory_out)
    );

    // Mux de escrita no registrador
    assign reg_write_data = (mem_to_reg) ? data_memory_out : alu_result;

endmodule

TestRiscV.v
`include "RiscVTop.v"

`timescale 1ns/1ps

module riscv_tb();

    reg clk = 0;
    reg reset = 1;
    integer i;

    // Instancia o top module
    riscv_top uut (
        .clk(clk),
        .reset(reset)
    );

    // Clock de 10ns
    always #5 clk = ~clk;

    // Inicialização do teste
    initial begin
        $dumpfile("riscv_tb.vcd");
        $dumpvars(0, riscv_tb);

        // === Fase 0: Reset inicial
        #10;
        reset = 0;

        // === Carrega instruções manualmente na instr_memory ===
        // Formato: <opcode> + campos. Todos em hexadecimal

        uut.RF.registers[4] = 32'h0000000B; // Inicializa x4 com um valor para testes
        uut.RF.registers[5] = 32'h0000000F; // Inicializa x5 com um valor para testes

        // 0x00: lb x5, 0(x0)          --> carrega byte da mem[0] para x5
        uut.IMEM.memory[0] = 32'h00000283;

        // 0x04: sb x5, 4(x0)         --> armazena byte de x5 na mem[4]
        uut.IMEM.memory[1] = 32'h00500223;

        // 0x08: sub x6, x5, x4       --> x6 = x5 - x4 = 00000004
        uut.IMEM.memory[2] = 32'h40428333;

        // 0x0C: and x7, x6, x6       --> x7 = x6 & x6 = 00000004
        uut.IMEM.memory[3] = 32'h006363B3;

        // 0x10: ori x8, x0, 0x0F0     --> x8 = 0 | 0x0F0
        uut.IMEM.memory[4] = 32'h0F006413;

        // 0x14: srl x9, x8, x6       --> x9 = x8 >> x6 (shift by 4 bits)
        uut.IMEM.memory[5] = 32'h006454B3;

        // 0x18: beq x5, x6, +4       --> se x5 == x6, pula instrucao (won't be taken since x5 != x6)
        uut.IMEM.memory[6] = 32'h00630263;

        // Add a NOP or another instruction after the branch
        uut.IMEM.memory[7] = 32'h00000013; // NOP (addi x0, x0, 0)

        // === Inicializa memória de dados com valor em 0x00
        uut.DMEM.memory[0] = 8'h0F; // byte para instrução lb

        //=== Roda por ciclos suficientes ===
        //Executa ciclo por ciclo para debug
        repeat(15) begin // Run enough cycles for all instructions
            #10;
            $display("Cycle %0d: PC=%h, Instr=%h", $time/10, uut.pc_current, uut.instruction);
            $display("  Opcode=%b, RegWrite=%b, rd=%d", uut.instruction[6:0], uut.reg_write, uut.instruction[11:7]);
            if (uut.reg_write) begin
                $display("  Writing %h to reg[%d]", uut.reg_write_data, uut.instruction[11:7]);
            end
            $display("  x5=%h, x6=%h, x7=%h, x8=%h, x9=%h", 
                     uut.RF.registers[5], uut.RF.registers[6], uut.RF.registers[7], 
                     uut.RF.registers[8], uut.RF.registers[9]);
            $display("");
        end

        // === Resultados esperados ===
        $display("x5 (lb):  %h (esperado: 0000000F)", uut.RF.registers[5]);
        $display("x6 (sub): %h (esperado: 00000004)", uut.RF.registers[6]);
        $display("x7 (and): %h (esperado: 00000004)", uut.RF.registers[7]);
        $display("x8 (ori): %h (esperado: 000000F0)", uut.RF.registers[8]);
        $display("x9 (srl): %h (esperado: 0000000F)", uut.RF.registers[9]); // F0 >> 4 = 0x0000000F
        $display("Mem[4] (sb): %h (esperado: 0000000F)", uut.DMEM.memory[4]);
        $display("Mem[0] (lb): %h (esperado: 0000000F)", uut.DMEM.memory[0]); // Verifica se o byte foi carregado corretamente

        // === Verifica o estado dos registradores ===
        $display("Estado dos registradores:");
        $display("x0: %h", uut.RF.registers[0]); // x0 deve ser sempre 0
        $display("x1: %h", uut.RF.registers[1]);
        $display("x2: %h", uut.RF.registers[2]);
        $display("x3: %h", uut.RF.registers[3]);
        $display("x4: %h", uut.RF.registers[4]);
        $display("x5: %h", uut.RF.registers[5]);
        $display("x6: %h", uut.RF.registers[6]);
        $display("x7: %h", uut.RF.registers[7]);
        $display("x8: %h", uut.RF.registers[8]);
        $display("x9: %h", uut.RF.registers[9]);
        $display("x10: %h", uut.RF.registers[10]);
        $display("x11: %h", uut.RF.registers[11]);
        $display("x12: %h", uut.RF.registers[12]);
        $display("x13: %h", uut.RF.registers[13]);
        $display("x14: %h", uut.RF.registers[14]);
        $display("x15: %h", uut.RF.registers[15]);
        $display("x16: %h", uut.RF.registers[16]);
        $display("x17: %h", uut.RF.registers[17]);
        $display("x18: %h", uut.RF.registers[18]);
        $display("x19: %h", uut.RF.registers[19]);
        $display("x20: %h", uut.RF.registers[20]);
        $display("x21: %h", uut.RF.registers[21]);
        $display("x22: %h", uut.RF.registers[22]);
        $display("x23: %h", uut.RF.registers[23]);
        $display("x24: %h", uut.RF.registers[24]);
        $display("x25: %h", uut.RF.registers[25]);
        $display("x26: %h", uut.RF.registers[26]);
        $display("x27: %h", uut.RF.registers[27]);
        $display("x28: %h", uut.RF.registers[28]);
        $display("x29: %h", uut.RF.registers[29]);
        $display("x30: %h", uut.RF.registers[30]);
        $display("x31: %h", uut.RF.registers[31]);

        $finish; // Finaliza a simulação

    end
endmodule

riscv_tb.vcd
$date
	Sun Jul 27 22:47:57 2025
$end
$version
	Icarus Verilog
$end
$timescale
	1ps
$end
$scope module riscv_tb $end
$var reg 1 ! clk $end
$var reg 1 " reset $end
$scope module uut $end
$var wire 1 ! clk $end
$var wire 1 # load_byte $end
$var wire 1 " reset $end
$var wire 1 $ store_byte $end
$var wire 1 % zero $end
$var wire 5 & rs2 [4:0] $end
$var wire 5 ' rs1 [4:0] $end
$var wire 32 ( reg_write_data [31:0] $end
$var wire 1 ) reg_write $end
$var wire 32 * reg_data2 [31:0] $end
$var wire 32 + reg_data1 [31:0] $end
$var wire 5 , rd [4:0] $end
$var wire 32 - pc_plus4 [31:0] $end
$var wire 32 . pc_next [31:0] $end
$var wire 32 / pc_current [31:0] $end
$var wire 32 0 pc_branch [31:0] $end
$var wire 1 1 overflow $end
$var wire 7 2 opcode [6:0] $end
$var wire 1 3 mem_write $end
$var wire 1 4 mem_to_reg $end
$var wire 1 5 mem_read $end
$var wire 32 6 instruction [31:0] $end
$var wire 32 7 imm_out [31:0] $end
$var wire 7 8 funct7 [6:0] $end
$var wire 3 9 funct3 [2:0] $end
$var wire 32 : data_memory_out [31:0] $end
$var wire 1 ; carry $end
$var wire 1 < branch $end
$var wire 1 = alu_src $end
$var wire 32 > alu_result [31:0] $end
$var wire 2 ? alu_op [1:0] $end
$var wire 32 @ alu_in2 [31:0] $end
$var wire 4 A alu_ctrl [3:0] $end
$scope module ALU $end
$var wire 32 B b [31:0] $end
$var wire 4 C alu_ctrl [3:0] $end
$var wire 32 D a [31:0] $end
$var reg 1 ; carry $end
$var reg 1 1 overflow $end
$var reg 32 E result [31:0] $end
$var reg 1 % zero $end
$upscope $end
$scope module ALUCTRL $end
$var wire 3 F funct3 [2:0] $end
$var wire 7 G funct7 [6:0] $end
$var wire 2 H alu_op [1:0] $end
$var reg 4 I alu_ctrl [3:0] $end
$upscope $end
$scope module BRCTRL $end
$var wire 32 J pc_branch [31:0] $end
$var wire 32 K pc_plus_4 [31:0] $end
$var wire 1 % zero $end
$var wire 32 L pc_next [31:0] $end
$var wire 1 < branch $end
$upscope $end
$scope module CU $end
$var wire 7 M opcode [6:0] $end
$var reg 2 N alu_op [1:0] $end
$var reg 1 = alu_src $end
$var reg 1 < branch $end
$var reg 1 5 mem_read $end
$var reg 1 4 mem_to_reg $end
$var reg 1 3 mem_write $end
$var reg 1 ) reg_write $end
$upscope $end
$scope module DMEM $end
$var wire 32 O addr [31:0] $end
$var wire 1 ! clk $end
$var wire 1 # load_byte $end
$var wire 1 5 mem_read $end
$var wire 1 3 mem_write $end
$var wire 1 $ store_byte $end
$var wire 32 P write_data [31:0] $end
$var wire 12 Q byte_addr [11:0] $end
$var reg 32 R read_data [31:0] $end
$upscope $end
$scope module IMEM $end
$var wire 1 S clk $end
$var wire 32 T inst_input [31:0] $end
$var wire 32 U instruction [31:0] $end
$var wire 1 V write $end
$var wire 32 W addr [31:0] $end
$upscope $end
$scope module IMM $end
$var wire 32 X instr [31:0] $end
$var wire 7 Y opcode [6:0] $end
$var reg 32 Z imm_out [31:0] $end
$upscope $end
$scope module PCREG $end
$var wire 1 ! clk $end
$var wire 32 [ pc_in [31:0] $end
$var wire 1 " reset $end
$var reg 32 \ pc_out [31:0] $end
$upscope $end
$scope module RF $end
$var wire 1 ! clk $end
$var wire 5 ] rd [4:0] $end
$var wire 1 ) reg_write $end
$var wire 5 ^ rs1 [4:0] $end
$var wire 5 _ rs2 [4:0] $end
$var wire 32 ` write_data [31:0] $end
$var reg 32 a read_data1 [31:0] $end
$var reg 32 b read_data2 [31:0] $end
$var integer 32 c i [31:0] $end
$upscope $end
$upscope $end
$upscope $end
$enddefinitions $end
$comment Show the parameter values. $end
$dumpall
$end
#0
$dumpvars
b100000 c
bx b
bx a
bx `
bx _
bx ^
bx ]
b0 \
bx [
bx Z
bx Y
bx X
b0 W
zV
bx U
bz T
zS
bx R
bx Q
bx P
bx O
bx N
bx M
bx L
b100 K
bx J
bx I
bx H
bx G
bx F
bx E
bx D
bx C
bx B
bx A
bx @
bx ?
bx >
x=
x<
x;
bx :
bx 9
bx 8
bx 7
bx 6
x5
x4
x3
bx 2
x1
bx 0
b0 /
bx .
b100 -
bx ,
bx +
bx *
x)
bx (
bx '
bx &
x%
x$
x#
1"
0!
$end
#5000
1!
#10000
b0 Q
1%
b0 >
b0 E
b0 O
01
0;
b1111 (
b1111 `
b100 .
b100 L
b100 [
b0 @
b0 B
b0 *
b0 P
b0 b
b0 +
b0 D
b0 a
b10 A
b10 C
b10 I
1#
0$
0<
b0 ?
b0 H
b0 N
1=
03
15
14
1)
b1111 :
b1111 R
b0 0
b0 J
b0 7
b0 Z
b11 Y
b0 8
b0 G
b0 &
b0 _
b0 '
b0 ^
b0 9
b0 F
b101 ,
b101 ]
b11 2
b11 M
0!
b1010000011 6
b1010000011 U
b1010000011 X
0"
#15000
b1 Q
0%
b100 >
b100 E
b100 O
b0 :
b0 R
b100 (
b100 `
b100 @
b100 B
b1111 *
b1111 P
b1111 b
0#
1$
13
05
04
0)
b100 7
b100 Z
b100011 Y
b101 &
b101 _
b100 ,
b100 ]
b100011 2
b100011 M
b10100000000001000100011 6
b10100000000001000100011 U
b10100000000001000100011 X
b1000 .
b1000 L
b1000 [
b1000 0
b1000 J
b1000 -
b1000 K
b100 /
b100 W
b100 \
1!
#20000
0!
#25000
b1011 @
b1011 B
b110 A
b110 C
b110 I
b1011 *
b1011 P
b1011 b
b1111 +
b1111 D
b1111 a
0$
b10 ?
b10 H
b10 N
0=
03
1)
b0 7
b0 Z
b110011 Y
b100000 8
b100000 G
b100 &
b100 _
b101 '
b101 ^
b110 ,
b110 ]
b110011 2
b110011 M
b1000000010000101000001100110011 6
b1000000010000101000001100110011 U
b1000000010000101000001100110011 X
b1100 .
b1100 L
b1100 [
b1000 0
b1000 J
b1100 -
b1100 K
b1000 /
b1000 W
b1000 \
1!
#30000
0!
#35000
b1 Q
b100 (
b100 `
b100 @
b100 B
b100 >
b100 E
b100 O
b100 *
b100 P
b100 b
b100 +
b100 D
b100 a
b1 A
b1 C
b1 I
b0 8
b0 G
b110 &
b110 _
b110 '
b110 ^
b110 9
b110 F
b111 ,
b111 ]
b11000110110001110110011 6
b11000110110001110110011 U
b11000110110001110110011 X
b10000 .
b10000 L
b10000 [
b1100 0
b1100 J
b10000 -
b10000 K
b1100 /
b1100 W
b1100 \
1!
#40000
0!
#45000
b111100 Q
b11110000 (
b11110000 `
b11110000 >
b11110000 E
b11110000 O
b11110000 @
b11110000 B
b0 *
b0 P
b0 b
b0 +
b0 D
b0 a
1=
b11110000 7
b11110000 Z
b10011 Y
b111 8
b111 G
b10000 &
b10000 _
b0 '
b0 ^
b1000 ,
b1000 ]
b10011 2
b10011 M
b1111000000000110010000010011 6
b1111000000000110010000010011 U
b1111000000000110010000010011 X
b10100 .
b10100 L
b10100 [
b100000000 0
b100000000 J
b10100 -
b10100 K
b10000 /
b10000 W
b10000 \
1!
#50000
0!
#55000
b11 Q
b1111 (
b1111 `
b1111 >
b1111 E
b1111 O
b100 @
b100 B
b100 *
b100 P
b100 b
b11110000 +
b11110000 D
b11110000 a
b1001 A
b1001 C
b1001 I
0=
b0 7
b0 Z
b110011 Y
b0 8
b0 G
b110 &
b110 _
b1000 '
b1000 ^
b101 9
b101 F
b1001 ,
b1001 ]
b110011 2
b110011 M
b11001000101010010110011 6
b11001000101010010110011 U
b11001000101010010110011 X
b11000 .
b11000 L
b11000 [
b10100 0
b10100 J
b11000 -
b11000 K
b10100 /
b10100 W
b10100 \
1!
#60000
0!
#65000
b0 Q
b0 (
b0 `
1%
b0 >
b0 E
b0 O
b100 +
b100 D
b100 a
b110 A
b110 C
b110 I
1<
b1 ?
b1 H
b1 N
0)
b100 7
b100 Z
b1100011 Y
b110 '
b110 ^
b0 9
b0 F
b100 ,
b100 ]
b1100011 2
b1100011 M
b11000110000001001100011 6
b11000110000001001100011 U
b11000110000001001100011 X
b11100 .
b11100 L
b11100 [
b11100 0
b11100 J
b11100 -
b11100 K
b11000 /
b11000 W
b11000 \
1!
#70000
0!
#75000
b10 A
b10 C
b10 I
b0 @
b0 B
b0 *
b0 P
b0 b
b0 +
b0 D
b0 a
0<
b10 ?
b10 H
b10 N
1=
1)
b0 7
b0 Z
b10011 Y
b0 &
b0 _
b0 '
b0 ^
b0 ,
b0 ]
b10011 2
b10011 M
b10011 6
b10011 U
b10011 X
b100000 .
b100000 L
b100000 [
b11100 0
b11100 J
b100000 -
b100000 K
b11100 /
b11100 W
b11100 \
1!
#80000
0!
#85000
bx Q
bx (
bx `
x%
x1
x;
bx >
bx E
bx O
bx @
bx B
bx *
bx P
bx b
bx +
bx D
bx a
x#
x$
b0 ?
b0 H
b0 N
0=
0)
bx Y
bx 8
bx G
bx &
bx _
bx '
bx ^
bx 9
bx F
bx ,
bx ]
bx 2
bx M
bx 6
bx U
bx X
b100100 .
b100100 L
b100100 [
b100000 0
b100000 J
b100100 -
b100100 K
b100000 /
b100000 W
b100000 \
1!
#90000
0!
#95000
b101000 .
b101000 L
b101000 [
b100100 0
b100100 J
b101000 -
b101000 K
b100100 /
b100100 W
b100100 \
1!
#100000
0!
#105000
b101100 .
b101100 L
b101100 [
b101000 0
b101000 J
b101100 -
b101100 K
b101000 /
b101000 W
b101000 \
1!
#110000
0!
#115000
b110000 .
b110000 L
b110000 [
b101100 0
b101100 J
b110000 -
b110000 K
b101100 /
b101100 W
b101100 \
1!
#120000
0!
#125000
b110100 .
b110100 L
b110100 [
b110000 0
b110000 J
b110100 -
b110100 K
b110000 /
b110000 W
b110000 \
1!
#130000
0!
#135000
b111000 .
b111000 L
b111000 [
b110100 0
b110100 J
b111000 -
b111000 K
b110100 /
b110100 W
b110100 \
1!
#140000
0!
#145000
b111100 .
b111100 L
b111100 [
b111000 0
b111000 J
b111100 -
b111100 K
b111000 /
b111000 W
b111000 \
1!
#150000
0!
#155000
b1000000 .
b1000000 L
b1000000 [
b111100 0
b111100 J
b1000000 -
b1000000 K
b111100 /
b111100 W
b111100 \
1!
